{
  "timestamp": "2025-09-02T13:39:12.850Z",
  "summary": {
    "totalTests": 35,
    "passedTests": 19,
    "failedTests": 16,
    "successRate": 54,
    "deploymentReady": false
  },
  "categories": {
    "File Structure": {
      "passed": 9,
      "failed": 1,
      "warned": 0,
      "tests": [
        {
          "category": "File Structure",
          "test": "File exists: package.json",
          "status": "PASS",
          "details": "",
          "timestamp": "2025-09-02T13:39:12.670Z"
        },
        {
          "category": "File Structure",
          "test": "File exists: next.config.ts",
          "status": "PASS",
          "details": "",
          "timestamp": "2025-09-02T13:39:12.671Z"
        },
        {
          "category": "File Structure",
          "test": "File exists: tsconfig.json",
          "status": "PASS",
          "details": "",
          "timestamp": "2025-09-02T13:39:12.671Z"
        },
        {
          "category": "File Structure",
          "test": "File exists: prisma/schema.prisma",
          "status": "PASS",
          "details": "",
          "timestamp": "2025-09-02T13:39:12.672Z"
        },
        {
          "category": "File Structure",
          "test": "File exists: .env",
          "status": "PASS",
          "details": "",
          "timestamp": "2025-09-02T13:39:12.672Z"
        },
        {
          "category": "File Structure",
          "test": "File exists: app/layout.tsx",
          "status": "PASS",
          "details": "",
          "timestamp": "2025-09-02T13:39:12.672Z"
        },
        {
          "category": "File Structure",
          "test": "File missing: app/page.tsx",
          "status": "FAIL",
          "details": "Required file not found",
          "timestamp": "2025-09-02T13:39:12.673Z"
        },
        {
          "category": "File Structure",
          "test": "File exists: components/ui",
          "status": "PASS",
          "details": "",
          "timestamp": "2025-09-02T13:39:12.674Z"
        },
        {
          "category": "File Structure",
          "test": "File exists: lib/db.ts",
          "status": "PASS",
          "details": "",
          "timestamp": "2025-09-02T13:39:12.675Z"
        },
        {
          "category": "File Structure",
          "test": "File exists: middleware.ts",
          "status": "PASS",
          "details": "",
          "timestamp": "2025-09-02T13:39:12.675Z"
        }
      ]
    },
    "Dependencies": {
      "passed": 4,
      "failed": 1,
      "warned": 0,
      "tests": [
        {
          "category": "Dependencies",
          "test": "Dependency: next",
          "status": "PASS",
          "details": "15.4.4",
          "timestamp": "2025-09-02T13:39:12.676Z"
        },
        {
          "category": "Dependencies",
          "test": "Dependency: react",
          "status": "PASS",
          "details": "19.1.0",
          "timestamp": "2025-09-02T13:39:12.676Z"
        },
        {
          "category": "Dependencies",
          "test": "Dependency: prisma",
          "status": "FAIL",
          "details": "Missing critical dependency",
          "timestamp": "2025-09-02T13:39:12.676Z"
        },
        {
          "category": "Dependencies",
          "test": "Dependency: @clerk/nextjs",
          "status": "PASS",
          "details": "^6.26.0",
          "timestamp": "2025-09-02T13:39:12.676Z"
        },
        {
          "category": "Dependencies",
          "test": "Dependency: tailwindcss",
          "status": "PASS",
          "details": "^4",
          "timestamp": "2025-09-02T13:39:12.676Z"
        }
      ]
    },
    "Environment": {
      "passed": 3,
      "failed": 0,
      "warned": 0,
      "tests": [
        {
          "category": "Environment",
          "test": "Environment Variable: DATABASE_URL",
          "status": "PASS",
          "details": "Present in .env file",
          "timestamp": "2025-09-02T13:39:12.677Z"
        },
        {
          "category": "Environment",
          "test": "Environment Variable: NEXT_PUBLIC_CLERK_PUBLISHABLE_KEY",
          "status": "PASS",
          "details": "Present in .env file",
          "timestamp": "2025-09-02T13:39:12.677Z"
        },
        {
          "category": "Environment",
          "test": "Environment Variable: CLERK_SECRET_KEY",
          "status": "PASS",
          "details": "Present in .env file",
          "timestamp": "2025-09-02T13:39:12.677Z"
        }
      ]
    },
    "Page Availability": {
      "passed": 0,
      "failed": 6,
      "warned": 3,
      "tests": [
        {
          "category": "Page Availability",
          "test": "Page Load: Home Page",
          "status": "FAIL",
          "details": "Network error: fetch failed",
          "timestamp": "2025-09-02T13:39:12.785Z"
        },
        {
          "category": "Page Availability",
          "test": "Page Load: Sign In Page",
          "status": "FAIL",
          "details": "Network error: fetch failed",
          "timestamp": "2025-09-02T13:39:12.789Z"
        },
        {
          "category": "Page Availability",
          "test": "Page Load: Sign Up Page",
          "status": "FAIL",
          "details": "Network error: fetch failed",
          "timestamp": "2025-09-02T13:39:12.794Z"
        },
        {
          "category": "Page Availability",
          "test": "Page Load: Admin Dashboard",
          "status": "FAIL",
          "details": "Network error: fetch failed",
          "timestamp": "2025-09-02T13:39:12.798Z"
        },
        {
          "category": "Page Availability",
          "test": "Page Load: Link Shortener",
          "status": "FAIL",
          "details": "Network error: fetch failed",
          "timestamp": "2025-09-02T13:39:12.801Z"
        },
        {
          "category": "Page Availability",
          "test": "Page Load: Admin Overview",
          "status": "WARN",
          "details": "Network error: fetch failed",
          "timestamp": "2025-09-02T13:39:12.804Z"
        },
        {
          "category": "Page Availability",
          "test": "Page Load: Admin Settings",
          "status": "WARN",
          "details": "Network error: fetch failed",
          "timestamp": "2025-09-02T13:39:12.810Z"
        },
        {
          "category": "Page Availability",
          "test": "Page Load: Shortener API",
          "status": "FAIL",
          "details": "Network error: fetch failed",
          "timestamp": "2025-09-02T13:39:12.813Z"
        },
        {
          "category": "Page Availability",
          "test": "Page Load: OG Data API",
          "status": "WARN",
          "details": "Network error: fetch failed",
          "timestamp": "2025-09-02T13:39:12.820Z"
        }
      ]
    },
    "API Endpoints": {
      "passed": 0,
      "failed": 1,
      "warned": 1,
      "tests": [
        {
          "category": "API Endpoints",
          "test": "Link Shortener API",
          "status": "FAIL",
          "details": "fetch failed",
          "timestamp": "2025-09-02T13:39:12.829Z"
        },
        {
          "category": "API Endpoints",
          "test": "OG Data API",
          "status": "WARN",
          "details": "fetch failed",
          "timestamp": "2025-09-02T13:39:12.832Z"
        }
      ]
    },
    "Database": {
      "passed": 0,
      "failed": 1,
      "warned": 0,
      "tests": [
        {
          "category": "Database",
          "test": "Database Connectivity",
          "status": "FAIL",
          "details": "Cannot reach database endpoints",
          "timestamp": "2025-09-02T13:39:12.836Z"
        }
      ]
    },
    "Security": {
      "passed": 3,
      "failed": 0,
      "warned": 0,
      "tests": [
        {
          "category": "Security",
          "test": "Sensitive File Protection: .env",
          "status": "PASS",
          "details": "File properly protected",
          "timestamp": "2025-09-02T13:39:12.840Z"
        },
        {
          "category": "Security",
          "test": "Sensitive File Protection: package.json",
          "status": "PASS",
          "details": "File properly protected",
          "timestamp": "2025-09-02T13:39:12.842Z"
        },
        {
          "category": "Security",
          "test": "Sensitive File Protection: prisma/schema.prisma",
          "status": "PASS",
          "details": "File properly protected",
          "timestamp": "2025-09-02T13:39:12.845Z"
        }
      ]
    },
    "Performance": {
      "passed": 0,
      "failed": 2,
      "warned": 0,
      "tests": [
        {
          "category": "Performance",
          "test": "Page Load Time: Home Page",
          "status": "FAIL",
          "details": "fetch failed",
          "timestamp": "2025-09-02T13:39:12.848Z"
        },
        {
          "category": "Performance",
          "test": "Page Load Time: Admin Dashboard",
          "status": "FAIL",
          "details": "fetch failed",
          "timestamp": "2025-09-02T13:39:12.850Z"
        }
      ]
    }
  },
  "errors": [
    "File Structure: File missing: app/page.tsx - Required file not found",
    "Dependencies: Dependency: prisma - Missing critical dependency",
    "Page Availability: Page Load: Home Page - Network error: fetch failed",
    "Page Availability: Page Load: Sign In Page - Network error: fetch failed",
    "Page Availability: Page Load: Sign Up Page - Network error: fetch failed",
    "Page Availability: Page Load: Admin Dashboard - Network error: fetch failed",
    "Page Availability: Page Load: Link Shortener - Network error: fetch failed",
    "Page Availability: Page Load: Shortener API - Network error: fetch failed",
    "API Endpoints: Link Shortener API - fetch failed",
    "Database: Database Connectivity - Cannot reach database endpoints",
    "Performance: Page Load Time: Home Page - fetch failed",
    "Performance: Page Load Time: Admin Dashboard - fetch failed"
  ],
  "warnings": [
    "Page Availability: Page Load: Admin Overview - Network error: fetch failed",
    "Page Availability: Page Load: Admin Settings - Network error: fetch failed",
    "Page Availability: Page Load: OG Data API - Network error: fetch failed",
    "API Endpoints: OG Data API - fetch failed"
  ],
  "recommendations": [
    "🔴 CRITICAL: Fix all failed tests before deployment",
    "🔴 Success rate below 80% - extensive fixes needed"
  ]
}